<?xml version="1.0" encoding="utf-8" ?>
<ResearchProjectDefs>

	<ResearchProjectDef>
	    <defName>RH_TemperatureControlHeating</defName>
	    <label>Industrial heating</label>
	    <description>Allows you to build industrial heaters.</description>
	    <baseCost>1500</baseCost>
		<techLevel>Industrial</techLevel>
		<prerequisites>
		  <li>Electricity</li>
		</prerequisites>
	</ResearchProjectDef>
	
	<ResearchProjectDef>
	    <defName>RH_TemperatureControlCooling</defName>
	    <label>Industrial cooling</label>
	    <description>Allows you to build industrial coolers.</description>
	    <baseCost>1500</baseCost>
		<techLevel>Industrial</techLevel>
		<prerequisites>
			<li>AirConditioning</li>
		</prerequisites>
	</ResearchProjectDef>

</ResearchProjectDefs>
